paddle_serving_app/__init__.py
paddle_serving_app/local_predict.py
paddle_serving_app/package.py
paddle_serving_app/trace.py
paddle_serving_app/version.py
paddle_serving_app/models/__init__.py
paddle_serving_app/models/model_list.py
paddle_serving_app/proto/__init__.py
paddle_serving_app/proto/general_model_config_pb2.py
paddle_serving_app/proto/general_model_service_pb2.py
paddle_serving_app/proto/general_model_service_pb2_grpc.py
paddle_serving_app/reader/__init__.py
paddle_serving_app/reader/batching.py
paddle_serving_app/reader/bert_base_reader.py
paddle_serving_app/reader/chinese_bert_reader.py
paddle_serving_app/reader/functional.py
paddle_serving_app/reader/image_reader.py
paddle_serving_app/reader/imdb_reader.py
paddle_serving_app/reader/lac_reader.py
paddle_serving_app/reader/ocr_reader.py
paddle_serving_app/reader/pptsn_reader.py
paddle_serving_app/reader/reader.py
paddle_serving_app/reader/senta_reader.py
paddle_serving_app/reader/test_image_reader.py
paddle_serving_app/reader/test_preprocess.py
paddle_serving_app/reader/tokenization.py
paddle_serving_app/reader/pddet/__init__.py
paddle_serving_app/reader/pddet/image_tool.py
paddle_serving_app/utils/__init__.py
paddle_serving_app/utils/arr2image.py
paddle_serving_app-0.9.0.dist-info/METADATA
paddle_serving_app-0.9.0.dist-info/WHEEL
paddle_serving_app-0.9.0.dist-info/top_level.txt
paddle_serving_app-0.9.0.dist-info/RECORD
